.travis.yml
README.rst
setup.py
tox.ini
mr/__init__.py
mr.awsome.ec2.egg-info/PKG-INFO
mr.awsome.ec2.egg-info/SOURCES.txt
mr.awsome.ec2.egg-info/dependency_links.txt
mr.awsome.ec2.egg-info/entry_points.txt
mr.awsome.ec2.egg-info/namespace_packages.txt
mr.awsome.ec2.egg-info/not-zip-safe
mr.awsome.ec2.egg-info/requires.txt
mr.awsome.ec2.egg-info/top_level.txt
mr/awsome_ec2/__init__.py
mr/awsome_ec2/test_ec2.py