Metadata-Version: 1.0
Name: mr.awsome.ec2
Version: 1.0b1
Summary: A plugin for mr.awsome providing integration with Amazon EC2.
Home-page: http://github.com/fschulze/mr.awsome.ec2
Author: Florian Schulze
Author-email: florian.schulze@gmx.net
License: UNKNOWN
Platform: UNKNOWN
